{
	"configurations" : 
	[
		{
			"directories" : 
			[
				{
					"build" : ".",
					"childIndexes" : 
					[
						1,
						2,
						3,
						4
					],
					"hasInstallRule" : true,
					"jsonFile" : "directory-.-Debug-f5ebdc15457944623624.json",
					"minimumCMakeVersion" : 
					{
						"string" : "3.22"
					},
					"projectIndex" : 0,
					"source" : "."
				},
				{
					"build" : "lib",
					"hasInstallRule" : true,
					"jsonFile" : "directory-lib-Debug-bfda5c21046afe9a437b.json",
					"minimumCMakeVersion" : 
					{
						"string" : "3.22"
					},
					"parentIndex" : 0,
					"projectIndex" : 0,
					"source" : "lib",
					"targetIndexes" : 
					[
						1
					]
				},
				{
					"build" : "examples",
					"jsonFile" : "directory-examples-Debug-1c8b83b621b6ef38a245.json",
					"minimumCMakeVersion" : 
					{
						"string" : "3.22"
					},
					"parentIndex" : 0,
					"projectIndex" : 0,
					"source" : "examples",
					"targetIndexes" : 
					[
						2
					]
				},
				{
					"build" : "tests",
					"jsonFile" : "directory-tests-Debug-b01f6abb0ab61427ef3b.json",
					"minimumCMakeVersion" : 
					{
						"string" : "3.22"
					},
					"parentIndex" : 0,
					"projectIndex" : 0,
					"source" : "tests",
					"targetIndexes" : 
					[
						3
					]
				},
				{
					"build" : "python",
					"jsonFile" : "directory-python-Debug-8db83237229819026e8d.json",
					"minimumCMakeVersion" : 
					{
						"string" : "3.22"
					},
					"parentIndex" : 0,
					"projectIndex" : 0,
					"source" : "python",
					"targetIndexes" : 
					[
						0
					]
				}
			],
			"name" : "Debug",
			"projects" : 
			[
				{
					"directoryIndexes" : 
					[
						0,
						1,
						2,
						3,
						4
					],
					"name" : "accurate_ri",
					"targetIndexes" : 
					[
						0,
						1,
						2,
						3
					]
				}
			],
			"targets" : 
			[
				{
					"directoryIndex" : 4,
					"id" : "_accurate_ri::@e1ac5446165bc0cf31e4",
					"jsonFile" : "target-_accurate_ri-Debug-88a82ce48d70d0a6136d.json",
					"name" : "_accurate_ri",
					"projectIndex" : 0
				},
				{
					"directoryIndex" : 1,
					"id" : "accurate_ri::@306ed2d68c6501e8728f",
					"jsonFile" : "target-accurate_ri-Debug-383158bf3c14723ff207.json",
					"name" : "accurate_ri",
					"projectIndex" : 0
				},
				{
					"directoryIndex" : 2,
					"id" : "examples::@714eac15f71a94114fdf",
					"jsonFile" : "target-examples-Debug-f3af06ba21e6eaab7920.json",
					"name" : "examples",
					"projectIndex" : 0
				},
				{
					"directoryIndex" : 3,
					"id" : "run_tests::@a44f0ac069e85531cdee",
					"jsonFile" : "target-run_tests-Debug-d1b0858343aedf264990.json",
					"name" : "run_tests",
					"projectIndex" : 0
				}
			]
		}
	],
	"kind" : "codemodel",
	"paths" : 
	{
		"build" : "/home/samuel.soutullo/GitHub/AccurateRI/cmake-build-debug",
		"source" : "/home/samuel.soutullo/GitHub/AccurateRI"
	},
	"version" : 
	{
		"major" : 2,
		"minor" : 3
	}
}
